classifier_model/VERSION
classifier_model/__init__.py
classifier_model/config.yml
classifier_model/pipeline.py
classifier_model/predict.py
classifier_model/train_pipeline.py
classifier_model/config/__init__.py
classifier_model/config/core.py
classifier_model/datasets/__init__.py
classifier_model/datasets/test.csv
classifier_model/datasets/train.csv
classifier_model/processing/__init__.py
classifier_model/processing/data_manager.py
classifier_model/processing/validation.py
classifier_model/trained_models/__init__.py
classifier_model/trained_models/classifier_model_output_v3.0.0.pkl
heart_dissease_classifier_dgcr-3.0.0.dist-info/METADATA
heart_dissease_classifier_dgcr-3.0.0.dist-info/WHEEL
heart_dissease_classifier_dgcr-3.0.0.dist-info/top_level.txt
heart_dissease_classifier_dgcr-3.0.0.dist-info/RECORD
